simpleaudio/functionchecks.py
simpleaudio/__init__.py
simpleaudio/_simpleaudio.pypy38-pp73-darwin.so
simpleaudio/shiny.py
simpleaudio/test_audio/c.wav
simpleaudio/test_audio/g.wav
simpleaudio/test_audio/e.wav
simpleaudio/test_audio/notes_2_16_44.wav
simpleaudio/test_audio/left_right.wav
simpleaudio_patched-1.0.5.dist-info/RECORD
simpleaudio_patched-1.0.5.dist-info/WHEEL
simpleaudio_patched-1.0.5.dist-info/top_level.txt
simpleaudio_patched-1.0.5.dist-info/LICENSE.txt
simpleaudio_patched-1.0.5.dist-info/METADATA
