Metadata-Version: 2.1
Name: simpleaudio-patched
Version: 1.0.5
Summary: Simple, asynchronous audio playback for Python 3.
Author-email: Joe Hamilton <jhamilton10@georgefox.edu>, Harco Kuppens <h.kuppens@cs.ru.nl>
License: /*
Project-URL: Homepage, https://github.com/harcokuppens/py-simple-audio
Keywords: audio,wave,media,multimedia,sound,alsa,coreaudio,winmm,music
Classifier: License :: OSI Approved :: MIT License
Classifier: Programming Language :: Python :: 3
Classifier: Topic :: Multimedia :: Sound/Audio
Classifier: Operating System :: POSIX :: Linux
Classifier: Operating System :: Microsoft :: Windows
Classifier: Operating System :: MacOS :: MacOS X
License-File: LICENSE.txt
